dataviewer/__init__.py
dataviewer/customSlider.cpython-312-x86_64-linux-gnu.so
dataviewer/dataExport.cpython-312-x86_64-linux-gnu.so
dataviewer/dataExportRead.cpython-312-x86_64-linux-gnu.so
dataviewer/floatingWidget.cpython-312-x86_64-linux-gnu.so
dataviewer/globalData.cpython-312-x86_64-linux-gnu.so
dataviewer/graphWidget2.cpython-312-x86_64-linux-gnu.so
dataviewer/log_config.cpython-312-x86_64-linux-gnu.so
dataviewer/mainWindow.cpython-312-x86_64-linux-gnu.so
dataviewer/pyqtTimer.cpython-312-x86_64-linux-gnu.so
dataviewer/qt_compat_exec.cpython-312-x86_64-linux-gnu.so
dataviewer/tableWidget.cpython-312-x86_64-linux-gnu.so
dataviewer/tagCfgDiag.cpython-312-x86_64-linux-gnu.so
dataviewer/timeCtrlWidget.cpython-312-x86_64-linux-gnu.so
dataviewer/tsdata_np.cpython-312-x86_64-linux-gnu.so
dataviewer/tsdbConnDiag.cpython-312-x86_64-linux-gnu.so
dataviewer/pics/dataviewer_red_icon.ico
dataviewer/pics/pause.svg
dataviewer/pics/play.svg
taiji_dataviewer-5.1.0.dist-info/METADATA
taiji_dataviewer-5.1.0.dist-info/WHEEL
taiji_dataviewer-5.1.0.dist-info/top_level.txt
taiji_dataviewer-5.1.0.dist-info/RECORD
