Metadata-Version: 2.4
Name: taiji-dataviewer
Version: 5.1.0
Summary: DataViewer GUI tools for Tai-Ji Ccontrol
Author-email: Kangkang Zhang <kkzhang3@hotmail.com>
Requires-Python: >=3.12
Requires-Dist: PyQt5>=5.15
Requires-Dist: loguru
Requires-Dist: pillow
Requires-Dist: psycopg
Requires-Dist: psycopg-binary
Requires-Dist: pyqtgraph
Requires-Dist: QDarkStyle
Requires-Dist: QtPy
Requires-Dist: tsdbpy
Requires-Dist: taiji-hasp
Provides-Extra: dev
Requires-Dist: pytest; extra == "dev"
Requires-Dist: black; extra == "dev"
Requires-Dist: mypy; extra == "dev"
